blowtorch/__init__.py
blowtorch/cli.py
blowtorch/export_weights.py
blowtorch/generate_models.py
blowtorch/layers/__init__.py
blowtorch/layers/_convolutions.py
blowtorch/layers/_flatten.py
blowtorch/layers/_interfaces.py
blowtorch/layers/_linear.py
blowtorch/layers/_parsing.py
blowtorch/layers/_relu.py
blowtorch/schema/model-schema.schema
blowtorch/templates/models_template.py.jinja2
blowtorch/templates/models_template.rs.jinja2
blowtorch_py-0.1.3.dist-info/entry_points.txt
blowtorch_py-0.1.3.dist-info/WHEEL
blowtorch_py-0.1.3.dist-info/METADATA
blowtorch_py-0.1.3.dist-info/RECORD
