Metadata-Version: 2.1
Name: blowtorch-py
Version: 0.1.3
Summary: A framework for creating Rust machine learning models that are trained in Python.
License: MIT
Author: Conzel
Author-email: 38732545+Conzel@users.noreply.github.com
Requires-Python: >=3.9,<4.0
Classifier: License :: OSI Approved :: MIT License
Classifier: Programming Language :: Python :: 3
Classifier: Programming Language :: Python :: 3.10
Classifier: Programming Language :: Python :: 3.9
Requires-Dist: Jinja2 (>=3.1.1,<4.0.0)
Requires-Dist: jsonschema (>=4.4.0,<5.0.0)
Requires-Dist: torch (>=1.11.0,<2.0.0)
Project-URL: Documentation, https://blowtorch.readthedocs.io/en/latest/
